{"generator_version":"0.1.0","model_schema_version":"1.0","runtime_source_hash":"2aace3efeb30267bc974641d7cf4e7eca9b48f747dcbe815f3f29018cb58de78","schema":{"$defs":{"EvidenceRef":{"additionalProperties":false,"properties":{"evidence_id":{"pattern":"^[A-Za-z0-9][A-Za-z0-9._-]{0,127}$","title":"Evidence Id","type":"string"},"locator":{"title":"Locator","type":"string"},"provenance":{"enum":["host_observed","coordinator_observed","agent_reported"],"title":"Provenance","type":"string"},"summary":{"title":"Summary","type":"string"}},"required":["evidence_id","provenance","locator","summary"],"title":"EvidenceRef","type":"object"}},"additionalProperties":false,"properties":{"evidence":{"items":{"$ref":"#/$defs/EvidenceRef"},"title":"Evidence","type":"array"},"expected_effect_ids_observed":{"items":{"type":"string"},"title":"Expected Effect Ids Observed","type":"array"},"next_strategy":{"anyOf":[{"type":"string"},{"type":"null"}],"title":"Next Strategy"},"operation_id":{"pattern":"^[A-Za-z0-9][A-Za-z0-9._-]{0,127}$","title":"Operation Id","type":"string"},"schema_version":{"const":"1.0","title":"Schema Version","type":"string"},"success":{"title":"Success","type":"boolean"},"unexpected_effects":{"items":{"type":"string"},"title":"Unexpected Effects","type":"array"}},"required":["schema_version","operation_id","success","evidence","expected_effect_ids_observed","unexpected_effects","next_strategy"],"title":"ExecutionReport","type":"object"},"schema_payload_hash":"34eeabf8216033086604700c2311fea632f95c612cb7c2e8dfa795a1622519df"}
