{"generator_version":"0.1.0","model_schema_version":"1.0","runtime_source_hash":"2aace3efeb30267bc974641d7cf4e7eca9b48f747dcbe815f3f29018cb58de78","schema":{"$defs":{"NetworkPolicyGrant":{"additionalProperties":false,"properties":{"approval_classes":{"items":{"type":"string"},"title":"Approval Classes","type":"array"},"credential_audiences":{"items":{"type":"string"},"title":"Credential Audiences","type":"array"},"destinations":{"items":{"type":"string"},"title":"Destinations","type":"array"},"grant_id":{"pattern":"^[A-Za-z0-9][A-Za-z0-9._-]{0,127}$","title":"Grant Id","type":"string"},"idempotency_required":{"title":"Idempotency Required","type":"boolean"},"max_bytes":{"minimum":0,"title":"Max Bytes","type":"integer"},"max_calls":{"minimum":0,"title":"Max Calls","type":"integer"},"max_seconds":{"minimum":0,"title":"Max Seconds","type":"integer"},"methods":{"items":{"type":"string"},"title":"Methods","type":"array"},"ports":{"items":{"maximum":65535,"minimum":1,"type":"integer"},"title":"Ports","type":"array"},"protocols":{"items":{"enum":["http","https","tcp"],"type":"string"},"title":"Protocols","type":"array"},"redirect_destinations":{"items":{"type":"string"},"title":"Redirect Destinations","type":"array"},"request_data_classes":{"items":{"type":"string"},"title":"Request Data Classes","type":"array"},"response_data_classes":{"items":{"type":"string"},"title":"Response Data Classes","type":"array"},"retry_limit":{"minimum":0,"title":"Retry Limit","type":"integer"},"semantics":{"items":{"enum":["read","write"],"type":"string"},"title":"Semantics","type":"array"}},"required":["grant_id","destinations","ports","protocols","methods","semantics","request_data_classes","response_data_classes","credential_audiences","redirect_destinations","max_calls","max_bytes","max_seconds","retry_limit","idempotency_required","approval_classes"],"title":"NetworkPolicyGrant","type":"object"}},"additionalProperties":false,"properties":{"deny_adapters":{"items":{"type":"string"},"title":"Deny Adapters","type":"array"},"deny_command_forms":{"items":{"type":"string"},"title":"Deny Command Forms","type":"array"},"deny_effect_classes":{"items":{"type":"string"},"title":"Deny Effect Classes","type":"array"},"deny_operations":{"items":{"type":"string"},"title":"Deny Operations","type":"array"},"intersect_environment_names":{"anyOf":[{"items":{"type":"string"},"type":"array"},{"type":"null"}],"title":"Intersect Environment Names"},"intersect_executable_hashes":{"anyOf":[{"items":{"type":"string"},"type":"array"},{"type":"null"}],"title":"Intersect Executable Hashes"},"intersect_network_grants":{"anyOf":[{"items":{"$ref":"#/$defs/NetworkPolicyGrant"},"type":"array"},{"type":"null"}],"title":"Intersect Network Grants"},"intersect_path_roots":{"anyOf":[{"items":{"type":"string"},"type":"array"},{"type":"null"}],"title":"Intersect Path Roots"},"lower_maximums":{"additionalProperties":{"anyOf":[{"type":"integer"},{"type":"string"}]},"title":"Lower Maximums","type":"object"},"require_approvals":{"items":{"type":"string"},"title":"Require Approvals","type":"array"},"require_evidence_sources":{"items":{"type":"string"},"title":"Require Evidence Sources","type":"array"},"require_minimum_enforcement":{"additionalProperties":{"enum":["instruction_only","host_enforced"],"type":"string"},"title":"Require Minimum Enforcement","type":"object"},"require_minimum_observation":{"additionalProperties":{"enum":["agent_reported","coordinator_observed","host_observed"],"type":"string"},"title":"Require Minimum Observation","type":"object"},"require_verification":{"items":{"type":"string"},"title":"Require Verification","type":"array"},"schema_version":{"const":"1.0","title":"Schema Version","type":"string"}},"required":["schema_version","deny_operations","deny_adapters","deny_effect_classes","deny_command_forms","intersect_path_roots","intersect_executable_hashes","intersect_network_grants","intersect_environment_names","lower_maximums","require_approvals","require_minimum_enforcement","require_minimum_observation","require_evidence_sources","require_verification"],"title":"ProjectPolicy","type":"object"},"schema_payload_hash":"c5edae6da73e4a23e74a804215abf65af633e4dfbffd8f29550d7fbbfe8658fe"}
